spicelib/__init__.py
spicelib/client_server/__init__.py
spicelib/client_server/sim_client.py
spicelib/client_server/sim_server.py
spicelib/client_server/srv_sim_runner.py
spicelib/editor/__init__.py
spicelib/editor/asc_editor.py
spicelib/editor/asy_reader.py
spicelib/editor/base_editor.py
spicelib/editor/base_schematic.py
spicelib/editor/ltspice_utils.py
spicelib/editor/qsch_editor.py
spicelib/editor/spice_editor.py
spicelib/editor/updates.py
spicelib/log/__init__.py
spicelib/log/logfile_data.py
spicelib/log/ltsteps.py
spicelib/log/qspice_log_reader.py
spicelib/log/semi_dev_op_reader.py
spicelib/raw/__init__.py
spicelib/raw/plot_data.py
spicelib/raw/plot_interface.py
spicelib/raw/raw_classes.py
spicelib/raw/raw_read.py
spicelib/raw/raw_write.py
spicelib/scripts/asc_to_qsch.py
spicelib/scripts/asc_to_qsch_data.xml
spicelib/scripts/histogram.py
spicelib/scripts/ltsteps.py
spicelib/scripts/raw_convert.py
spicelib/scripts/rawplot.py
spicelib/scripts/readme_update.py
spicelib/scripts/run_server.py
spicelib/sim/__init__.py
spicelib/sim/process_callback.py
spicelib/sim/run_task.py
spicelib/sim/sim_runner.py
spicelib/sim/sim_stepping.py
spicelib/sim/simulator.py
spicelib/sim/tookit/__init__.py
spicelib/sim/tookit/fast_worst_case.py
spicelib/sim/tookit/montecarlo.py
spicelib/sim/tookit/quick_sensitivity_analysis.py
spicelib/sim/tookit/sim_analysis.py
spicelib/sim/tookit/tolerance_deviations.py
spicelib/sim/tookit/worst_case.py
spicelib/simulators/__init__.py
spicelib/simulators/ltspice_simulator.py
spicelib/simulators/ngspice_simulator.py
spicelib/simulators/qspice_simulator.py
spicelib/simulators/xyce_simulator.py
spicelib/utils/detect_encoding.py
spicelib/utils/file_search.py
spicelib/utils/sweep_iterators.py
spicelib/utils/windows_short_names.py
spicelib-1.4.9.dist-info/METADATA
spicelib-1.4.9.dist-info/WHEEL
spicelib-1.4.9.dist-info/entry_points.txt
spicelib-1.4.9.dist-info/licenses/LICENSE
spicelib-1.4.9.dist-info/RECORD
