Metadata-Version: 2.4
Name: spicelib
Version: 1.4.9
Summary: A set of tools to Automate Spice simulations
License: GPL-3.0
License-File: LICENSE
Keywords: spice,ltspice,qspice,ngspice,electronic simulator,montecarlo,worst-case
Author: Nuno Brum
Author-email: nuno.brum@gmail.com
Requires-Python: >=3.9,<4.0
Classifier: License :: OSI Approved :: GNU General Public License v3 (GPLv3)
Classifier: Programming Language :: Python :: 3
Classifier: Programming Language :: Python :: 3.9
Classifier: Programming Language :: Python :: 3.10
Classifier: Programming Language :: Python :: 3.11
Classifier: Programming Language :: Python :: 3.12
Classifier: Programming Language :: Python :: 3.13
Classifier: Programming Language :: Python :: 3.14
Requires-Dist: clipin
Requires-Dist: matplotlib
Requires-Dist: numpy
Requires-Dist: psutil
Requires-Dist: scipy
Project-URL: author, https://www.nunobrum.com/
Project-URL: bug-tracker, https://github.com/nunobrum/spicelib/issues
Project-URL: homepage, https://github.com/nunobrum/spicelib
Project-URL: repository, https://github.com/nunobrum/spicelib.git
